Pynite/Analysis.py
Pynite/BeamSegY.py
Pynite/BeamSegZ.py
Pynite/FEModel3D.py
Pynite/FixedEndReactions.py
Pynite/LoadCombo.py
Pynite/MainStyleSheet.css
Pynite/MatFoundation.py
Pynite/Material.py
Pynite/Member3D.py
Pynite/Mesh.py
Pynite/Node3D.py
Pynite/PhysMember.py
Pynite/Plate3D.py
Pynite/Quad3D.py
Pynite/Rendering.py
Pynite/Report_Template.html
Pynite/Reporting.py
Pynite/Section.py
Pynite/ShearWall.py
Pynite/Spring3D.py
Pynite/Tri3D.py
Pynite/VTKWriter.py
Pynite/Visualization.py
Pynite/__init__.py
pynitefea-2.2.1.dist-info/licenses/LICENSE
pynitefea-2.2.1.dist-info/METADATA
pynitefea-2.2.1.dist-info/WHEEL
pynitefea-2.2.1.dist-info/top_level.txt
pynitefea-2.2.1.dist-info/RECORD
