Metadata-Version: 2.4
Name: PyNiteFEA
Version: 2.2.1
Summary: A simple elastic 3D structural finite element library for Python.
Home-page: https://github.com/JWock82/Pynite.git
Author: D. Craig Brinck, PE, SE
Author-email: Building.Code@outlook.com
Classifier: Programming Language :: Python :: 3
Classifier: Programming Language :: Python :: 3.11
Classifier: Programming Language :: Python :: 3.12
Classifier: Programming Language :: Python :: 3.13
Classifier: License :: OSI Approved :: MIT License
Classifier: Operating System :: OS Independent
Requires-Python: >=3.11
License-File: LICENSE
Requires-Dist: numpy>=2.4.0
Requires-Dist: PrettyTable
Requires-Dist: scipy
Requires-Dist: matplotlib
Provides-Extra: all
Requires-Dist: Ipython; extra == "all"
Requires-Dist: vtk>=9.3.0; extra == "all"
Requires-Dist: pyvista[all,trame]>=0.43.4; extra == "all"
Requires-Dist: trame_jupyter_extension; extra == "all"
Requires-Dist: ipywidgets; extra == "all"
Requires-Dist: pdfkit; extra == "all"
Requires-Dist: Jinja2; extra == "all"
Provides-Extra: vtk
Requires-Dist: IPython; extra == "vtk"
Requires-Dist: vtk>=9.3.0; extra == "vtk"
Provides-Extra: pyvista
Requires-Dist: pyvista[all,trame]>=0.43.4; extra == "pyvista"
Requires-Dist: trame_jupyter_extension; extra == "pyvista"
Requires-Dist: ipywidgets; extra == "pyvista"
Provides-Extra: reporting
Requires-Dist: pdfkit; extra == "reporting"
Requires-Dist: Jinja2; extra == "reporting"
Provides-Extra: derivations
Requires-Dist: jupyterlab; extra == "derivations"
Requires-Dist: sympy; extra == "derivations"
Dynamic: author
Dynamic: author-email
Dynamic: classifier
Dynamic: description
Dynamic: description-content-type
Dynamic: home-page
Dynamic: license-file
Dynamic: provides-extra
Dynamic: requires-dist
Dynamic: requires-python
Dynamic: summary
